OptimizationTestFunctions/__init__.py
OptimizationTestFunctions/functions.py
OptimizationTestFunctions/plot_func.py
OptimizationTestFunctions/transformations.py
OptimizationTestFunctions-1.0.1.dist-info/METADATA
OptimizationTestFunctions-1.0.1.dist-info/WHEEL
OptimizationTestFunctions-1.0.1.dist-info/top_level.txt
OptimizationTestFunctions-1.0.1.dist-info/RECORD
