Metadata-Version: 2.1
Name: OptimizationTestFunctions
Version: 1.0.1
Summary: PyPI package containing collection of optimization test functions and some useful methods for working with them
Home-page: https://github.com/PasaOpasen/OptimizationTestFunctions
Author: Demetry Pascal
Author-email: qtckpuhdsa@gmail.com
Maintainer: ['Demetry Pascal']
License: UNKNOWN
Keywords: optimization,evolutionary algorithms,fast,easy,evolution,generator,test,test-functions,3D,functions
Platform: UNKNOWN
Classifier: Programming Language :: Python :: 3
Classifier: License :: OSI Approved :: MIT License
Classifier: Operating System :: OS Independent
Classifier: Topic :: Software Development :: Libraries :: Python Modules
